robomeshcat/__init__.py
robomeshcat/human.py
robomeshcat/object.py
robomeshcat/robot.py
robomeshcat/scene.py
robomeshcat-1.1.3.dist-info/LICENSE
robomeshcat-1.1.3.dist-info/METADATA
robomeshcat-1.1.3.dist-info/WHEEL
robomeshcat-1.1.3.dist-info/top_level.txt
robomeshcat-1.1.3.dist-info/RECORD
