Metadata-Version: 2.1
Name: robomeshcat
Version: 1.1.3
Summary: RoboMeshCat - Set of utilities for visualizing robots in web-based visualizer MeshCat.
Author-email: Vladimir Petrik <vladimir.petrik@cvut.cz>
License: BSD-2-Clause
Project-URL: Homepage, https://github.com/petrikvladimir/RoboMeshCat
Project-URL: Bug Tracker, https://github.com/petrikvladimir/RoboMeshCat/issues
Classifier: Topic :: Scientific/Engineering :: Visualization
Classifier: Framework :: Robot Framework
Requires-Python: >=3.7
License-File: LICENSE
Requires-Dist: pin
Requires-Dist: meshcat
Requires-Dist: trimesh
Requires-Dist: imageio
Requires-Dist: imageio-ffmpeg
Provides-Extra: dev
Requires-Dist: pycollada; extra == "dev"
